talosbot/__init__.py
talosbot/logs.py
talosbot/talos.py
talosbot/channels/__init__.py
talosbot/channels/abstract_channel.py
talosbot/channels/cli.py
talosbot/channels/slack.py
talosbot/channels/telegram.py
talosbot/cli/__init__.py
talosbot/cli/entrypoint.py
talosbot/matchers/__init__.py
talosbot/matchers/abstract_matcher.py
talosbot/matchers/bert.py
talosbot/matchers/exceptions.py
talosbot/matchers/regex.py
talosbot/parsers/__init__.py
talosbot/parsers/abstract_parser.py
talosbot/parsers/exceptions.py
talosbot/parsers/ner.py
talosbot/parsers/regex.py
talosbot-0.2.0.dist-info/licenses/LICENSE
talosbot-0.2.0.dist-info/METADATA
talosbot-0.2.0.dist-info/WHEEL
talosbot-0.2.0.dist-info/entry_points.txt
talosbot-0.2.0.dist-info/top_level.txt
talosbot-0.2.0.dist-info/RECORD
