Metadata-Version: 2.4
Name: talosbot
Version: 0.2.0
Summary: Talos chatops framework
Home-page: https://github.com/talosbotoss/talosbot
Author: Sergio Perez Rodriguez
Author-email: sergiopr89@gmail.com
License: MIT
Classifier: Programming Language :: Python :: 3
Classifier: Operating System :: OS Independent
Requires-Python: >=3.8
License-File: LICENSE
Requires-Dist: jsonschema
Requires-Dist: python-telegram-bot
Requires-Dist: sentence-transformers
Requires-Dist: spacy
Requires-Dist: spacy-transformers
Requires-Dist: spacy-lookups-data
Requires-Dist: slack-bolt
Dynamic: license-file
